{"swagger":"2.0","info":{"description":"Componente transversal que la interaccion con juego de ruleta. \n\nTecnologias:1.-) Java: 11\n2.-) Spring-Boot: 2.3.0.RELEASE\n3.-) Encoding: UTF8\n4.-) URL PROXY - GITHUB: https://github.com/yahercarrillo/mezubo\n6.-) Contacto - yahercarrillo@gmail.com\n","version":"1.0.0","title":"MEZUBO - TEST YAHER CARRILLO"},"host":"localhost:8081","tags":[{"name":"business-controller","description":"Business Controller"},{"name":"user-controller","description":"User Controller"}],"paths":{"/storage/v1/roulette":{"get":{"tags":["business-controller"],"summary":"getAll","operationId":"getAllUsingGET","produces":["*/*"],"responses":{"200":{"description":"OK","schema":{"type":"object"}}}}},"/storage/v1/roulette/closeRoulette/{id}":{"get":{"tags":["business-controller"],"summary":"closeRoulette","operationId":"closeRouletteUsingGET","produces":["*/*"],"parameters":[{"name":"id","in":"path","description":"id","required":true,"type":"string"}],"responses":{"200":{"description":"OK"}}}},"/storage/v1/roulette/code/{code}":{"get":{"tags":["business-controller"],"summary":"FindByCode","description":"Consulta de una mesa por su codigo unico","operationId":"getByCodeUsingGET","produces":["*/*"],"parameters":[{"name":"code","in":"path","description":"code","required":true,"type":"string"}],"responses":{"200":{"description":"200","schema":{"type":"object"}},"404":{"description":"404"}}}},"/storage/v1/roulette/create":{"post":{"tags":["business-controller"],"summary":"create Roulette","description":"Crea una mesa de juego","operationId":"createRouletteUsingPOST","consumes":["application/json"],"produces":["*/*"],"parameters":[{"in":"body","name":"emp","description":"emp","required":true,"schema":{"$ref":"#/definitions/MzbRoulette"}}],"responses":{"200":{"description":"200","schema":{"type":"object"}},"302":{"description":"302"}}}},"/storage/v1/roulette/createBet":{"post":{"tags":["business-controller"],"summary":"create Bet","description":"Crea una apuesta","operationId":"createBetUsingPOST","consumes":["application/json"],"produces":["*/*"],"parameters":[{"name":"Authorization","in":"header","description":"Authorization","required":true,"type":"string"},{"in":"body","name":"emp","description":"emp","required":true,"schema":{"$ref":"#/definitions/MzbRouletteBets"}}],"responses":{"200":{"description":"200"},"302":{"description":"302"},"422":{"description":"422"},"423":{"description":"423"}}}},"/storage/v1/roulette/id/{id}":{"get":{"tags":["business-controller"],"summary":"FindById","description":"Consulta de una mesa por su id","operationId":"getByIdUsingGET","produces":["*/*"],"parameters":[{"name":"id","in":"path","description":"id","required":true,"type":"string"}],"responses":{"200":{"description":"200","schema":{"type":"object"}},"404":{"description":"404"}}}},"/storage/v1/roulette/openRoulette/{id}":{"get":{"tags":["business-controller"],"summary":"openRoulette","operationId":"openRouletteUsingGET","produces":["*/*"],"parameters":[{"name":"id","in":"path","description":"id","required":true,"type":"string"}],"responses":{"200":{"description":"OK"}}}},"/storage/v1/roulette/spinRoulette/{id}":{"get":{"tags":["business-controller"],"summary":"spinRoulette","operationId":"spinRouletteUsingGET","produces":["*/*"],"parameters":[{"name":"id","in":"path","description":"id","required":true,"type":"string"}],"responses":{"200":{"description":"OK","schema":{"$ref":"#/definitions/SpinWinner"}}}}},"/storage/v1/roulette/updateBet":{"put":{"tags":["business-controller"],"summary":"create Bet","description":"Crea una apuesta","operationId":"updateBetUsingPUT","consumes":["application/json"],"produces":["*/*"],"parameters":[{"name":"Authorization","in":"header","description":"Authorization","required":true,"type":"string"},{"in":"body","name":"emp","description":"emp","required":true,"schema":{"$ref":"#/definitions/MzbRouletteBets"}}],"responses":{"200":{"description":"200"},"302":{"description":"302"},"422":{"description":"422"},"423":{"description":"423"}}}},"/storage/v1/users":{"get":{"tags":["user-controller"],"summary":"getAll","operationId":"getAllUsingGET_1","produces":["*/*"],"responses":{"200":{"description":"OK","schema":{"type":"object"}}}},"post":{"tags":["user-controller"],"summary":"create User","description":"Crea un usuario para juegos","operationId":"createUserUsingPOST","consumes":["application/json"],"produces":["*/*"],"parameters":[{"in":"body","name":"emp","description":"emp","required":true,"schema":{"$ref":"#/definitions/MzbUsers"}}],"responses":{"200":{"description":"200"},"302":{"description":"302"}}},"put":{"tags":["user-controller"],"summary":"Update User","description":"Actualiza un usuario para juegos","operationId":"updateUserUsingPUT","consumes":["application/json"],"produces":["*/*"],"parameters":[{"in":"body","name":"emp","description":"emp","required":true,"schema":{"$ref":"#/definitions/MzbUsers"}}],"responses":{"200":{"description":"200"},"404":{"description":"404"}}}},"/storage/v1/users/{nickname}":{"get":{"tags":["user-controller"],"summary":"FindByNickName","description":"Consulta un usuario por su nombre unico","operationId":"FindByNickNameUsingGET","produces":["*/*"],"parameters":[{"name":"nickname","in":"path","description":"nickname","required":true,"type":"string"}],"responses":{"200":{"description":"200","schema":{"type":"object"}},"404":{"description":"404"}}}}},"definitions":{"MzbRoulette":{"type":"object","required":["code"],"properties":{"code":{"type":"string"},"datecreate":{"type":"string","format":"date-time"},"dateupdate":{"type":"string","format":"date-time"},"description":{"type":"string"},"enable":{"type":"boolean"},"id":{"type":"string"}},"title":"MzbRoulette"},"MzbRouletteBets":{"type":"object","required":["id_roulette","money","numbergame"],"properties":{"id":{"type":"string"},"id_roulette":{"type":"string"},"money":{"type":"number"},"numbergame":{"type":"integer","format":"int32"},"usergame":{"type":"string"}},"title":"MzbRouletteBets"},"MzbUsers":{"type":"object","required":["nickname"],"properties":{"credit":{"type":"number"},"datecreate":{"type":"string","format":"date-time"},"dateupdate":{"type":"string","format":"date-time"},"description":{"type":"string"},"enable":{"type":"boolean"},"id":{"type":"string"},"nickname":{"type":"string"}},"title":"MzbUsers"},"SpinWinner":{"type":"object","properties":{"amount":{"type":"number"},"color":{"type":"string"},"listWinnersPartial":{"type":"array","items":{"$ref":"#/definitions/MzbRouletteBets"}},"number":{"type":"integer","format":"int32"},"person":{"type":"string"},"roulette":{"type":"string"}},"title":"SpinWinner"}}}